odoo/addons/account_bank_statement_import_txt_xlsx/README.rst
odoo/addons/account_bank_statement_import_txt_xlsx/__init__.py
odoo/addons/account_bank_statement_import_txt_xlsx/__manifest__.py
odoo/addons/account_bank_statement_import_txt_xlsx/data/map_data.xml
odoo/addons/account_bank_statement_import_txt_xlsx/i18n/account_bank_statement_import_txt_xlsx.pot
odoo/addons/account_bank_statement_import_txt_xlsx/i18n/fr.po
odoo/addons/account_bank_statement_import_txt_xlsx/i18n/nl.po
odoo/addons/account_bank_statement_import_txt_xlsx/i18n/zh_CN.po
odoo/addons/account_bank_statement_import_txt_xlsx/models/__init__.py
odoo/addons/account_bank_statement_import_txt_xlsx/models/account_bank_statement_import.py
odoo/addons/account_bank_statement_import_txt_xlsx/models/account_bank_statement_import_sheet_mapping.py
odoo/addons/account_bank_statement_import_txt_xlsx/models/account_bank_statement_import_sheet_parser.py
odoo/addons/account_bank_statement_import_txt_xlsx/models/account_journal.py
odoo/addons/account_bank_statement_import_txt_xlsx/readme/CONFIGURE.rst
odoo/addons/account_bank_statement_import_txt_xlsx/readme/CONTRIBUTORS.rst
odoo/addons/account_bank_statement_import_txt_xlsx/readme/DESCRIPTION.rst
odoo/addons/account_bank_statement_import_txt_xlsx/readme/HISTORY.rst
odoo/addons/account_bank_statement_import_txt_xlsx/readme/USAGE.rst
odoo/addons/account_bank_statement_import_txt_xlsx/security/ir.model.access.csv
odoo/addons/account_bank_statement_import_txt_xlsx/static/description/icon.png
odoo/addons/account_bank_statement_import_txt_xlsx/static/description/index.html
odoo/addons/account_bank_statement_import_txt_xlsx/tests/__init__.py
odoo/addons/account_bank_statement_import_txt_xlsx/tests/test_account_bank_statement_import_txt_xlsx.py
odoo/addons/account_bank_statement_import_txt_xlsx/tests/fixtures/balance.csv
odoo/addons/account_bank_statement_import_txt_xlsx/tests/fixtures/debit_credit.csv
odoo13_addon_account_bank_statement_import_txt_xlsx-13.0.2.0.1.dist-info/METADATA
odoo13_addon_account_bank_statement_import_txt_xlsx-13.0.2.0.1.dist-info/WHEEL
odoo13_addon_account_bank_statement_import_txt_xlsx-13.0.2.0.1.dist-info/top_level.txt
odoo13_addon_account_bank_statement_import_txt_xlsx-13.0.2.0.1.dist-info/RECORD
