Metadata-Version: 2.1
Name: odoo13-addon-account-bank-statement-import-txt-xlsx
Version: 13.0.2.0.1
Summary: Import TXT/CSV or XLSX files as Bank Statements in Odoo
Home-page: https://github.com/OCA/bank-statement-import
Author: ForgeFlow, CorporateHub, Odoo Community Association (OCA)
Author-email: support@odoo-community.org
License: AGPL-3
Platform: UNKNOWN
Classifier: Programming Language :: Python
Classifier: Framework :: Odoo
Classifier: Framework :: Odoo :: 13.0
Classifier: License :: OSI Approved :: GNU Affero General Public License v3
Requires-Python: >=3.5
Requires-Dist: chardet
Requires-Dist: odoo13-addon-multi-step-wizard
Requires-Dist: odoo13-addon-web-widget-dropdown-dynamic
Requires-Dist: odoo (<13.1dev,>=13.0a)
Requires-Dist: xlrd
